{
  "meta": {
    "title": "いのち短し善せよ乙女"
  },
  "list": [
    {
      "order": 12,
      "isCover": false,
      "isColor": true,
      "isDouble": false,
      "isGuest": true,
      "issue": "2019-08"
    },
    {
      "order": 14,
      "isCover": false,
      "isColor": false,
      "isDouble": false,
      "isGuest": true,
      "issue": "2019-09"
    },
    {
      "order": 8,
      "isCover": false,
      "isColor": false,
      "isDouble": false,
      "isGuest": true,
      "issue": "2019-10"
    },
    {
      "order": 13,
      "isCover": false,
      "isColor": true,
      "isDouble": false,
      "isGuest": false,
      "issue": "2019-12"
    },
    {
      "order": 7,
      "isCover": false,
      "isColor": false,
      "isDouble": false,
      "isGuest": false,
      "issue": "2020-01"
    },
    {
      "order": 8,
      "isCover": false,
      "isColor": false,
      "isDouble": false,
      "isGuest": false,
      "issue": "2020-02"
    },
    {
      "order": 8,
      "isCover": false,
      "isColor": false,
      "isDouble": false,
      "isGuest": false,
      "issue": "2020-03"
    },
    {
      "order": 21,
      "isCover": false,
      "isColor": true,
      "isDouble": false,
      "isGuest": false,
      "issue": "2020-04"
    },
    {
      "order": 10,
      "isCover": false,
      "isColor": false,
      "isDouble": false,
      "isGuest": false,
      "issue": "2020-05"
    }
  ]
}
